setup.py
rhotimie3421/Binomialdistribution.py
rhotimie3421/Gaussiandistribution.py
rhotimie3421/Generaldistribution.py
rhotimie3421/__init__.py
rhotimie3421.egg-info/PKG-INFO
rhotimie3421.egg-info/SOURCES.txt
rhotimie3421.egg-info/dependency_links.txt
rhotimie3421.egg-info/not-zip-safe
rhotimie3421.egg-info/top_level.txt