Metadata-Version: 1.0
Name: rhotimie3421
Version: 0.1
Summary: Gaussian distributions test
Home-page: UNKNOWN
Author: UNKNOWN
Author-email: UNKNOWN
License: UNKNOWN
Platform: UNKNOWN
